mmdnn/__init__.py
mmdnn/conversion/__init__.py
mmdnn/conversion/_script/IRToCode.py
mmdnn/conversion/_script/IRToModel.py
mmdnn/conversion/_script/__init__.py
mmdnn/conversion/_script/convert.py
mmdnn/conversion/_script/convertToIR.py
mmdnn/conversion/_script/dump_code.py
mmdnn/conversion/_script/extractModel.py
mmdnn/conversion/caffe/__init__.py
mmdnn/conversion/caffe/caffe_emitter.py
mmdnn/conversion/caffe/caffe_pb2.py
mmdnn/conversion/caffe/common_graph.py
mmdnn/conversion/caffe/errors.py
mmdnn/conversion/caffe/graph.py
mmdnn/conversion/caffe/mapper.py
mmdnn/conversion/caffe/network.py
mmdnn/conversion/caffe/resolver.py
mmdnn/conversion/caffe/saver.py
mmdnn/conversion/caffe/shape.py
mmdnn/conversion/caffe/transformer.py
mmdnn/conversion/caffe/utils.py
mmdnn/conversion/caffe/writer.py
mmdnn/conversion/cntk/__init__.py
mmdnn/conversion/cntk/cntk_emitter.py
mmdnn/conversion/cntk/cntk_graph.py
mmdnn/conversion/cntk/cntk_parser.py
mmdnn/conversion/cntk/saver.py
mmdnn/conversion/common/__init__.py
mmdnn/conversion/common/utils.py
mmdnn/conversion/common/DataStructure/__init__.py
mmdnn/conversion/common/DataStructure/emitter.py
mmdnn/conversion/common/DataStructure/graph.py
mmdnn/conversion/common/DataStructure/parser.py
mmdnn/conversion/common/IR/IR_graph.py
mmdnn/conversion/common/IR/__init__.py
mmdnn/conversion/common/IR/graph_pb2.py
mmdnn/conversion/coreml/__init__.py
mmdnn/conversion/coreml/coreml_emitter.py
mmdnn/conversion/coreml/coreml_graph.py
mmdnn/conversion/coreml/coreml_parser.py
mmdnn/conversion/coreml/coreml_utils.py
mmdnn/conversion/darknet/__init__.py
mmdnn/conversion/darknet/cfg.py
mmdnn/conversion/darknet/darknet_graph.py
mmdnn/conversion/darknet/darknet_parser.py
mmdnn/conversion/darknet/darknet_utils.py
mmdnn/conversion/darknet/prototxt.py
mmdnn/conversion/examples/__init__.py
mmdnn/conversion/examples/extractor.py
mmdnn/conversion/examples/imagenet_test.py
mmdnn/conversion/examples/caffe/__init__.py
mmdnn/conversion/examples/caffe/extract_model.py
mmdnn-0.3.1.dist-info/LICENSE
mmdnn-0.3.1.dist-info/METADATA
mmdnn-0.3.1.dist-info/WHEEL
mmdnn-0.3.1.dist-info/entry_points.txt
mmdnn-0.3.1.dist-info/top_level.txt
mmdnn-0.3.1.dist-info/RECORD
