Metadata-Version: 2.1
Name: mmdnn
Version: 0.3.1
Summary: Deep learning model converter, visualization and editor.
Home-page: https://github.com/Microsoft/MMdnn
Author: System Research Group, Microsoft Research Asia
Author-email: mmdnn_feedback@microsoft.com
License: MIT
Keywords: deep learning model converter visualization
Platform: UNKNOWN
Classifier: Development Status :: 3 - Alpha
Classifier: Intended Audience :: Developers
Classifier: Intended Audience :: Education
Classifier: Intended Audience :: Science/Research
Classifier: Topic :: Scientific/Engineering :: Mathematics
Classifier: Topic :: Software Development :: Libraries :: Python Modules
Classifier: Topic :: Software Development :: Libraries
Classifier: License :: OSI Approved :: MIT License
Classifier: Programming Language :: Python :: 3
Requires-Dist: numpy (>=1.15.0)
Requires-Dist: protobuf (>=3.6.0)
Requires-Dist: six (>=1.10.0)
Requires-Dist: pillow (>=6.2.1)
